{
    "db_id": "mrext/nfc",
    "timestamp": 1705414808,
    "files": {
        "Scripts/nfc.sh": {
            "hash": "9211a953c6f09f938469c884111b88df",
            "size": 5848920,
            "url": "https://github.com/wizzomafizzo/mrext/releases/download/v20240116-1/nfc.sh",
            "reboot": false,
            "tags": [
                "nfc"
            ]
        },
        "Scripts/nfcui.sh": {
            "hash": "065efc478ed10e19d4f57a7a2611b8e0",
            "size": 47828,
            "url": "https://github.com/wizzomafizzo/mrext/releases/download/v20240116-1/nfcui.sh",
            "reboot": false,
            "tags": [
                "nfcui"
            ]
        }
    },
    "folders": {
        "Scripts/": {}
    }
}